mutclust/__init__.py
mutclust/__main__.py
mutclust/clustering.py
mutclust/mutual_rank.py
mutclust-0.1.4.dist-info/LICENSE
mutclust-0.1.4.dist-info/METADATA
mutclust-0.1.4.dist-info/WHEEL
mutclust-0.1.4.dist-info/entry_points.txt
mutclust-0.1.4.dist-info/top_level.txt
mutclust-0.1.4.dist-info/RECORD
