Metadata-Version: 2.1
Name: MutClust
Version: 0.1.4
Summary: MutClust: Mutual rank-based coexpression and clustering.
Author-email: Elly Poretsky <eporetsky@plantapp.org>
Keywords: bioinformatics,coexpression,mutual rank,clustering,RNA-seq
Classifier: Programming Language :: Python :: 3
Classifier: License :: OSI Approved :: MIT License
Classifier: Operating System :: POSIX :: Linux
Classifier: Topic :: Scientific/Engineering :: Bio-Informatics
Requires-Python: >=3.9
License-File: LICENSE
Requires-Dist: numpy==2.0.2
Requires-Dist: pandas==2.2.3
Requires-Dist: pynetcor==0.1.1
Requires-Dist: python-igraph==0.11.8
Requires-Dist: scikit-learn==1.6.1
Requires-Dist: pigz==2.9rc3
Requires-Dist: click
Provides-Extra: dev
Requires-Dist: pytest>=7.0.0; extra == "dev"
Requires-Dist: pytest-cov>=3.0.0; extra == "dev"
Requires-Dist: black>=22.0.0; extra == "dev"
Requires-Dist: flake8>=4.0.0; extra == "dev"
Requires-Dist: mypy>=0.900; extra == "dev"
Requires-Dist: pre-commit>=2.0.0; extra == "dev"
Provides-Extra: docs
Requires-Dist: sphinx>=4.0.0; extra == "docs"
Requires-Dist: sphinx-rtd-theme>=1.0.0; extra == "docs"
